Metadata-Version: 1.1
Name: torclient
Version: 1.0.6
Summary: A Simple, Lightweight and Easy To Use, TOR Proxy Library For Python
Home-page: https://github.com/noctua-github
Author: noctua
Author-email: psmall.775@gmail.com
License: UNKNOWN
Platform: UNKNOWN
Classifier: Programming Language :: Python
